eth/codecs/__init__.py
eth/codecs/abi/__init__.py
eth/codecs/abi/__main__.py
eth/codecs/abi/decoder.py
eth/codecs/abi/encoder.py
eth/codecs/abi/exceptions.py
eth/codecs/abi/nodes.py
eth/codecs/abi/parser.py
eth/codecs/abi/strategies/__init__.py
eth/codecs/abi/strategies/nodes.py
eth/codecs/abi/strategies/values.py
eth/codecs/utils.py
eth/hash.py
eth_stdlib-0.2.7.dist-info/COPYING
eth_stdlib-0.2.7.dist-info/COPYING.LESSER
eth_stdlib-0.2.7.dist-info/METADATA
eth_stdlib-0.2.7.dist-info/WHEEL
eth_stdlib-0.2.7.dist-info/RECORD
