Metadata-Version: 2.1
Name: eth-stdlib
Version: 0.2.7
Summary: Ethereum Standard Library for Python
Home-page: https://github.com/skellet0r/eth-stdlib
License: LGPL-3.0-only
Keywords: ethereum
Author: Edward Amor
Author-email: edward.amor3@gmail.com
Requires-Python: >=3.8,<4.0
Classifier: Intended Audience :: Developers
Classifier: License :: OSI Approved :: GNU Lesser General Public License v3 (LGPLv3)
Classifier: License :: OSI Approved :: GNU Lesser General Public License v3 or later (LGPLv3+)
Classifier: Programming Language :: Python :: 3
Classifier: Programming Language :: Python :: 3.8
Classifier: Programming Language :: Python :: 3.9
Classifier: Programming Language :: Python :: 3.10
Classifier: Programming Language :: Python :: 3.11
Classifier: Topic :: Software Development :: Libraries
Provides-Extra: hypothesis
Requires-Dist: hypothesis (>=6.58.0,<7.0.0) ; extra == "hypothesis"
Requires-Dist: pycryptodome (>=3.18.0,<4.0.0)
Project-URL: Documentation, https://eth-stdlib.readthedocs.io/en/latest
Project-URL: Repository, https://github.com/skellet0r/eth-stdlib
